odoo10_addon_stock_scanner_inventory-10.0.1.0.0.99.dev6-py3.8-nspkg.pth
odoo/addons/stock_scanner_inventory/README.rst
odoo/addons/stock_scanner_inventory/__init__.py
odoo/addons/stock_scanner_inventory/__manifest__.py
odoo/addons/stock_scanner_inventory/__openerp__.py
odoo/addons/stock_scanner_inventory/data/Inventory/Inventory.scenario
odoo/addons/stock_scanner_inventory/data/Inventory/scanner_scenario_step_inventory_done.py
odoo/addons/stock_scanner_inventory/data/Inventory/scanner_scenario_step_inventory_end_confirm.py
odoo/addons/stock_scanner_inventory/data/Inventory/scanner_scenario_step_inventory_location_selection.py
odoo/addons/stock_scanner_inventory/data/Inventory/scanner_scenario_step_inventory_product_code.py
odoo/addons/stock_scanner_inventory/data/Inventory/scanner_scenario_step_inventory_product_quantity.py
odoo/addons/stock_scanner_inventory/data/Inventory/scanner_scenario_step_inventory_unknown_location.py
odoo/addons/stock_scanner_inventory/data/Inventory/scanner_scenario_step_inventory_unknown_product.py
odoo/addons/stock_scanner_inventory/i18n/stock_scanner_inventory.pot
odoo/addons/stock_scanner_inventory/images/scenario.png
odoo/addons/stock_scanner_inventory/readme/CONTRIBUTORS.rst
odoo/addons/stock_scanner_inventory/readme/DESCRIPTION.rst
odoo/addons/stock_scanner_inventory/readme/INSTALL.rst
odoo/addons/stock_scanner_inventory/static/description/icon.png
odoo/addons/stock_scanner_inventory/static/description/index.html
odoo10_addon_stock_scanner_inventory-10.0.1.0.0.99.dev6.dist-info/METADATA
odoo10_addon_stock_scanner_inventory-10.0.1.0.0.99.dev6.dist-info/WHEEL
odoo10_addon_stock_scanner_inventory-10.0.1.0.0.99.dev6.dist-info/namespace_packages.txt
odoo10_addon_stock_scanner_inventory-10.0.1.0.0.99.dev6.dist-info/top_level.txt
odoo10_addon_stock_scanner_inventory-10.0.1.0.0.99.dev6.dist-info/RECORD
